json_criteria/__init__.py
json_criteria/all_meet_criteria.py
json_criteria/any_meet_criteria.py
json_criteria/apply_using_criteria.py
json_criteria/combine_criteria.py
json_criteria/config.py
json_criteria/filter_using_criteria.py
json_criteria/find_using_criteria.py
json_criteria/get_all_criteria.py
json_criteria/meets_criteria.py
json_criteria/internal/__init__.py
json_criteria/internal/compare.py
json_criteria/internal/meets_crit.py
json_criteria-0.2.0.dist-info/METADATA
json_criteria-0.2.0.dist-info/WHEEL
json_criteria-0.2.0.dist-info/licenses/LICENSE
json_criteria-0.2.0.dist-info/RECORD
