Metadata-Version: 2.3
Name: json-criteria
Version: 0.2.0
Summary: Python library designed for evaluating data against serializable JSON criteria
Project-URL: Homepage, https://github.com/MatthewFay/json-criteria
Project-URL: Issues, https://github.com/MatthewFay/json-criteria/issues
Author: Matthew Fay
License-File: LICENSE
Keywords: adaptable,compare,comparison,conditions,criteria,data evaluation,decision making,decision-making,decisions,dependency-free,dynamic adjustment,eligibility,evaluation,flexibility,flexible,json,logic,maintainability,maintainable,nested,nested conditions,operators,persistence,rules,serializable,serialization,serialized
Classifier: License :: OSI Approved :: MIT License
Classifier: Operating System :: OS Independent
Classifier: Programming Language :: Python :: 3
Requires-Python: >=3.8
